clickup_sdk/__init__.py
clickup_sdk/client.py
clickup_sdk/helpers.py
clickup_sdk/schemas.py
clickup_sdk/settings.py
clickup_sdk-1.0.dist-info/METADATA
clickup_sdk-1.0.dist-info/WHEEL
clickup_sdk-1.0.dist-info/RECORD
