Metadata-Version: 2.1
Name: clickup-sdk
Version: 1.0
Summary: 
Author: Marco Carmona
Author-email: marcocarmonapy@outlook.com
Requires-Python: >=3.10,<4.0
Classifier: Programming Language :: Python :: 3
Classifier: Programming Language :: Python :: 3.10
Classifier: Programming Language :: Python :: 3.11
Classifier: Programming Language :: Python :: 3.12
Requires-Dist: httpx (>=0.27.0,<0.28.0)
Requires-Dist: pydantic-settings (>=2.2.1,<3.0.0)
